aa_mumble_quick_connect/__init__.py
aa_mumble_quick_connect/admin.py
aa_mumble_quick_connect/apps.py
aa_mumble_quick_connect/auth_hooks.py
aa_mumble_quick_connect/dependency_checks.py
aa_mumble_quick_connect/models.py
aa_mumble_quick_connect/urls.py
aa_mumble_quick_connect/views.py
aa_mumble_quick_connect/locale/django.pot
aa_mumble_quick_connect/locale/cs_CZ/LC_MESSAGES/django.mo
aa_mumble_quick_connect/locale/cs_CZ/LC_MESSAGES/django.po
aa_mumble_quick_connect/locale/de/LC_MESSAGES/django.mo
aa_mumble_quick_connect/locale/de/LC_MESSAGES/django.po
aa_mumble_quick_connect/locale/es/LC_MESSAGES/django.mo
aa_mumble_quick_connect/locale/es/LC_MESSAGES/django.po
aa_mumble_quick_connect/locale/fr_FR/LC_MESSAGES/django.mo
aa_mumble_quick_connect/locale/fr_FR/LC_MESSAGES/django.po
aa_mumble_quick_connect/locale/it_IT/LC_MESSAGES/django.mo
aa_mumble_quick_connect/locale/it_IT/LC_MESSAGES/django.po
aa_mumble_quick_connect/locale/ja/LC_MESSAGES/django.mo
aa_mumble_quick_connect/locale/ja/LC_MESSAGES/django.po
aa_mumble_quick_connect/locale/ko_KR/LC_MESSAGES/django.mo
aa_mumble_quick_connect/locale/ko_KR/LC_MESSAGES/django.po
aa_mumble_quick_connect/locale/nl_NL/LC_MESSAGES/django.po
aa_mumble_quick_connect/locale/pl_PL/LC_MESSAGES/django.mo
aa_mumble_quick_connect/locale/pl_PL/LC_MESSAGES/django.po
aa_mumble_quick_connect/locale/ru/LC_MESSAGES/django.mo
aa_mumble_quick_connect/locale/ru/LC_MESSAGES/django.po
aa_mumble_quick_connect/locale/sk/LC_MESSAGES/django.po
aa_mumble_quick_connect/locale/uk/LC_MESSAGES/django.mo
aa_mumble_quick_connect/locale/uk/LC_MESSAGES/django.po
aa_mumble_quick_connect/locale/zh_Hans/LC_MESSAGES/django.mo
aa_mumble_quick_connect/locale/zh_Hans/LC_MESSAGES/django.po
aa_mumble_quick_connect/migrations/0001_initial.py
aa_mumble_quick_connect/migrations/0002_mumblelink_disable_url_verification.py
aa_mumble_quick_connect/migrations/__init__.py
aa_mumble_quick_connect/static/aa_mumble_quick_connect/libs/masonry-layout/4.2.2/masonry.pkgd.min.js
aa_mumble_quick_connect-1.1.1.dist-info/METADATA
aa_mumble_quick_connect-1.1.1.dist-info/WHEEL
aa_mumble_quick_connect-1.1.1.dist-info/licenses/LICENSE
aa_mumble_quick_connect-1.1.1.dist-info/RECORD
