Metadata-Version: 2.4
Name: aa-mumble-quick-connect
Version: 1.1.1
Summary: Quick connect links to your Mumble server channels
Project-URL: Changelog, https://github.com/ppfeufer/aa-mumble-quick-connect/blob/master/CHANGELOG.md
Project-URL: Codecov, https://codecov.io/gh/ppfeufer/aa-mumble-quick-connect
Project-URL: Discord, https://discord.gg/fjnHAmk
Project-URL: Documentation, https://github.com/ppfeufer/aa-mumble-quick-connect/blob/master/README.md
Project-URL: Donation, https://ko-fi.com/ppfeufer
Project-URL: GitHub, https://github.com/ppfeufer/aa-mumble-quick-connect
Project-URL: Tracker, https://github.com/ppfeufer/aa-mumble-quick-connect/issues
Project-URL: Translation, https://weblate.ppfeufer.de/projects/alliance-auth-apps/aa-mumble-quick-connect/
Author-email: Peter Pfeufer <develop@ppfeufer.de>
License:                     GNU GENERAL PUBLIC LICENSE
License-File: LICENSE
Keywords: allianceauth,mumble
Classifier: Environment :: Web Environment
Classifier: Framework :: Django
Classifier: Framework :: Django :: 4.2
Classifier: Intended Audience :: Developers
Classifier: License :: OSI Approved :: GNU General Public License v3 (GPLv3)
Classifier: Operating System :: OS Independent
Classifier: Programming Language :: Python
Classifier: Programming Language :: Python :: 3 :: Only
Classifier: Programming Language :: Python :: 3.10
Classifier: Programming Language :: Python :: 3.11
Classifier: Programming Language :: Python :: 3.12
Classifier: Programming Language :: Python :: 3.13
Classifier: Topic :: Internet :: WWW/HTTP
Classifier: Topic :: Internet :: WWW/HTTP :: Dynamic Content
Requires-Python: <3.14,>=3.10
Requires-Dist: allianceauth<5,>=4.10
Provides-Extra: tests-allianceauth-latest
Requires-Dist: coverage; extra == 'tests-allianceauth-latest'
Requires-Dist: django-webtest; extra == 'tests-allianceauth-latest'
